{
  "ScheduleConfigurationType": "Human",
  "ToleranceConfiguration": null,
  "Messages": [],
  "AssistanceQueue": {
    "Oid": "a6022b33-924c-4c98-861d-cdef75438d20",
    "Name": "DETRAN PE",
    "Attendants": [
      {
        "Oid": "3f1ef956-14ea-41ea-97bb-04cbf100c95f",
        "Name": "João Silva",
        "UserId": "joao.silva@gmail.com",
        "Cpf": "091.470.314-50",
        "ProfileImage":
            "https://api-dev.certfy.tech/onboarding/internal/api/Images/User/3f1ef956-14ea-41ea-97bb-04cbf100c95f",
        "Company": "94612025-d6f5-4951-91f0-118016d92944"
      },
      {
        "Oid": "03766257-e85e-45a9-bbcc-8f8f582053ea",
        "Name": "teste impressao digital",
        "UserId": "testeimpressao@gmail.com",
        "Cpf": "111.111.111-11",
        "ProfileImage":
            "https://api-dev.certfy.tech/onboarding/internal/api/Images/User/03766257-e85e-45a9-bbcc-8f8f582053ea",
        "Company": "94612025-d6f5-4951-91f0-118016d92944"
      }
    ],
    "AttendantNames": "Régis, João Silva, teste impressao digital",
    "DayOfWeeks": [
      {
        "DayOfWeek": "Sunday",
        "WorkTimeStart": "00:00:00",
        "WorkTimeEnd": "23:59:00",
        "QueueSize": 23
      }
    ]
  },
  "Oid": "58b4cd6f-e349-4675-976f-3536ca09c66d",
  "Name": "DETRAN PE - ABRIR PRIMEIRA HABILITAÇÃO ",
  "CompanyId": "94612025-d6f5-4951-91f0-118016d92944",
  "Order": 1,
  "UserIdentification": false,
  "TermsOfUseConfiguration": {
    "Oid": "463502f7-9d03-43ba-8500-63159f61060c",
    "Title": "DETRAN PE",
    "TermsOfUseText":
        "<h2 style=\"margin: 0px 0px 10px; font-family: DauphinPlain; line-height: 24px; text-align: left;\">What is Lorem Ipsum?</h2><p style=\"margin: 0px 0px 15px; text-align: justify; font-family: &quot;Open Sans&quot;, Arial, sans-serif; font-size: 14px;\"><strong>Lorem Ipsum</strong>&nbsp;is simply dummy text of the printing and typesetting industry. Lorem Ipsum has been the industry&#39;s standard dummy text ever since the 1500s, when an unknown printer took a galley of type and scrambled it to make a type specimen book. It has survived not only five centuries, but also the leap into electronic typesetting, remaining essentially unchanged. It was popularised in the 1960s with the release of Letraset sheets containing Lorem Ipsum passages, and more recently with desktop publishing software like Aldus PageMaker including versions of Lorem Ipsum.</p><h2 style=\"margin: 0px 0px 10px; font-family: DauphinPlain; line-height: 24px; text-align: left;\">Where does it come from?</h2><p style=\"margin: 0px 0px 15px; text-align: justify; font-family: &quot;Open Sans&quot;, Arial, sans-serif; font-size: 14px;\">Contrary to popular belief, Lorem Ipsum is not simply random text. It has roots in a piece of classical Latin literature from 45 BC, making it over 2000 years old. Richard McClintock, a Latin professor at Hampden-Sydney College in Virginia, looked up one of the more obscure Latin words, consectetur, from a Lorem Ipsum passage, and going through the cites of the word in classical literature, discovered the undoubtable source. Lorem Ipsum comes from sections 1.10.32 and 1.10.33 of &quot;de Finibus Bonorum et Malorum&quot; (The Extremes of Good and Evil) by Cicero, written in 45 BC. This book is a treatise on the theory of ethics, very popular during the Renaissance. The first line of Lorem Ipsum, &quot;Lorem ipsum dolor sit amet..&quot;, comes from a line in section 1.10.32.</p><p style=\"margin: 0px 0px 15px; text-align: justify; font-family: &quot;Open Sans&quot;, Arial, sans-serif; font-size: 14px;\">The standard chunk of Lorem Ipsum used since the 1500s is reproduced below for those interested. Sections 1.10.32 and 1.10.33 from &quot;de Finibus Bonorum et Malorum&quot; by Cicero are also reproduced in their exact original form, accompanied by English versions from the 1914 translation by H. Rackham.</p>",
    "DataConsentConfigurations": [
      {
        "Oid": "87935b99-d69d-48db-8ff2-927ee9a637da",
        "Title": "Dados pessoais",
        "DataConsentText": "Coletar dados pessoais",
        "DataConsentItemConfigurations": [
          {
            "Oid": "7b0c0491-dcc4-4f08-9311-439fc52b1a15",
            "Name": "CPF",
            "Description": "Coletar CPF\n",
            "DefaultAllowValue": false,
            "Mandatory": false
          }
        ]
      }
    ]
  },
  "ApplyScheduleCertificationIntegration": false,
  "ScheduleCertificationItengrationType": "IntegrationCertification",
  "CapturePlatform": "Full",
  "CaptureEntryConfigurations": [
    {
      "CaptureEntryType": "Fingerprint",
      "ValidateBiopassIDFeatures": false,
      "FingerPrintHand": "Right",
      "ApplyNFIQ": false,
      "Oid": "df933f43-ea83-488f-8a21-3c823fdbf163",
      "Mandatory": false,
      "Connect": false,
      "Caption": "Captura de digital direita",
      "Identifier": null,
      "Name": "Captura de digital Direita",
      "CompanyId": "94612025-d6f5-4951-91f0-118016d92944",
      "Order": 11
    },
    {
      "CaptureEntryType": "Fingerprint",
      "ValidateBiopassIDFeatures": false,
      "FingerPrintHand": "TwoThumbs",
      "ApplyNFIQ": false,
      "Oid": "a0e91747-51ca-449b-9f76-502566d5349f",
      "Mandatory": false,
      "Connect": false,
      "Caption": "polegares",
      "Identifier": null,
      "Name": "polegares",
      "CompanyId": "94612025-d6f5-4951-91f0-118016d92944",
      "Order": 10
    },
    {
      "CaptureEntryType": "Video",
      "RecordCall": false,
      "Oid": "24408612-a5f8-4073-8719-5e98d0002e85",
      "Mandatory": false,
      "Connect": false,
      "Caption": "Validação online",
      "Identifier": null,
      "Name": "Videoconferência",
      "CompanyId": "00000000-0000-0000-0000-000000000000",
      "Order": 9
    },
    {
      "CaptureEntryType": "Form",
      "Fields": [
        {
          "CaptureEntryType": "FormField",
          "Type": "Text",
          "Options": [],
          "FormFieldDynamic": {
            "Url": null,
            "FieldAttribute": null,
            "FormFieldDynamicControl": {
              "CaptureInput": "00000000-0000-0000-0000-000000000000",
              "VariableInput": null
            }
          },
          "OcrFieldName": "NULL",
          "InitialRange": 1,
          "FinalRange": 1,
          "SrcCep": false,
          "SrcCepField": false,
          "CorreiosField": "NULL",
          "FieldsForIntegration": "Null",
          "ExternalCapture": null,
          "Oid": "c614bf14-8764-4e7a-b3b9-0dd6e27a0a8d",
          "Mandatory": false,
          "Connect": false,
          "Caption": null,
          "Identifier": null,
          "Name": "Local para buscar primeira habilitação",
          "CompanyId":
              "Certfy.Remote.Admin.Models.BusinessObjects.CompanyXpo(94612025-d6f5-4951-91f0-118016d92944)",
          "Order": 3
        },
        {
          "CaptureEntryType": "FormField",
          "Type": "Text",
          "Options": [],
          "FormFieldDynamic": {
            "Url": null,
            "FieldAttribute": null,
            "FormFieldDynamicControl": {
              "CaptureInput": "00000000-0000-0000-0000-000000000000",
              "VariableInput": null
            }
          },
          "OcrFieldName": "NULL",
          "InitialRange": 1,
          "FinalRange": 1,
          "SrcCep": false,
          "SrcCepField": false,
          "CorreiosField": "NULL",
          "FieldsForIntegration": "Null",
          "ExternalCapture": null,
          "Oid": "0507c264-c3bb-43d8-87c8-802a1424b633",
          "Mandatory": false,
          "Connect": false,
          "Caption": null,
          "Identifier": null,
          "Name": "Observação",
          "CompanyId":
              "Certfy.Remote.Admin.Models.BusinessObjects.CompanyXpo(94612025-d6f5-4951-91f0-118016d92944)",
          "Order": 4
        },
        {
          "CaptureEntryType": "FormField",
          "Type": "Text",
          "Options": [],
          "FormFieldDynamic": {
            "Url": null,
            "FieldAttribute": null,
            "FormFieldDynamicControl": {
              "CaptureInput": "00000000-0000-0000-0000-000000000000",
              "VariableInput": null
            }
          },
          "OcrFieldName": "NULL",
          "InitialRange": 1,
          "FinalRange": 1,
          "SrcCep": false,
          "SrcCepField": false,
          "CorreiosField": "NULL",
          "FieldsForIntegration": "Null",
          "ExternalCapture": null,
          "Oid": "f5aa2456-3201-4c4a-92ed-85c8d607104a",
          "Mandatory": false,
          "Connect": false,
          "Caption": null,
          "Identifier": null,
          "Name": "Ponto de Atendimento",
          "CompanyId":
              "Certfy.Remote.Admin.Models.BusinessObjects.CompanyXpo(94612025-d6f5-4951-91f0-118016d92944)",
          "Order": 2
        },
        {
          "CaptureEntryType": "FormField",
          "Type": "Select",
          "Options": [
            {"Name": "AB", "Order": 1, "Selected": false, "LinkCapture": []},
            {"Name": "D", "Order": 1, "Selected": false, "LinkCapture": []},
            {"Name": "A", "Order": 1, "Selected": false, "LinkCapture": []},
            {"Name": "E", "Order": 1, "Selected": false, "LinkCapture": []},
            {"Name": "C", "Order": 1, "Selected": false, "LinkCapture": []},
            {"Name": "B", "Order": 1, "Selected": false, "LinkCapture": []}
          ],
          "FormFieldDynamic": {
            "Url": null,
            "FieldAttribute": null,
            "FormFieldDynamicControl": {
              "CaptureInput": "00000000-0000-0000-0000-000000000000",
              "VariableInput": null
            }
          },
          "OcrFieldName": "NULL",
          "InitialRange": 1,
          "FinalRange": 1,
          "SrcCep": false,
          "SrcCepField": false,
          "CorreiosField": "NULL",
          "FieldsForIntegration": "Null",
          "ExternalCapture": null,
          "Oid": "a63f658a-d389-4d5e-b0c7-d5c2255ca328",
          "Mandatory": false,
          "Connect": false,
          "Caption": null,
          "Identifier": null,
          "Name": "Categoria da Habilitação ",
          "CompanyId":
              "Certfy.Remote.Admin.Models.BusinessObjects.CompanyXpo(94612025-d6f5-4951-91f0-118016d92944)",
          "Order": 1
        }
      ],
      "IsExternalCapture": false,
      "OcrLink": false,
      "IdentificationDocumentCaptureEntryConfiguration": null,
      "Oid": "339f4895-9720-4fd6-923c-632ec996b5f6",
      "Mandatory": true,
      "Connect": false,
      "Caption": "Informe os dados da sua habilitação ",
      "Identifier": null,
      "Name": "Formulário de Dados de Habilitação ",
      "CompanyId": "94612025-d6f5-4951-91f0-118016d92944",
      "Order": 8
    },
    {
      "CaptureEntryType": "Fingerprint",
      "ValidateBiopassIDFeatures": true,
      "FingerPrintHand": "Left",
      "ApplyNFIQ": false,
      "Oid": "d5e32f5d-1e58-46e0-9db8-797ed493acea",
      "Mandatory": true,
      "Connect": false,
      "Caption": "Capture suas digitais da mão esquerda",
      "Identifier": null,
      "Name": "Capturar Impressão Digital - Mão Esquerda",
      "CompanyId": "94612025-d6f5-4951-91f0-118016d92944",
      "Order": 4
    },
    {
      "CaptureEntryType": "Face",
      "ValidateBiopassIDFeatures": true,
      "ValidateIcaoFeatures": true,
      "Oid": "f9f2a944-f3e3-42e3-a4f1-b13072cccd8e",
      "Mandatory": true,
      "Connect": false,
      "Caption": "Capture sua face ",
      "Identifier": null,
      "Name": "Coletar Face do Usuário",
      "CompanyId": "94612025-d6f5-4951-91f0-118016d92944",
      "Order": 1
    },
    {
      "CaptureEntryType": "Form",
      "Fields": [
        {
          "CaptureEntryType": "FormField",
          "Type": "Text",
          "Options": [],
          "FormFieldDynamic": {
            "Url": null,
            "FieldAttribute": null,
            "FormFieldDynamicControl": {
              "CaptureInput": "00000000-0000-0000-0000-000000000000",
              "VariableInput": null
            }
          },
          "OcrFieldName": "NULL",
          "InitialRange": 1,
          "FinalRange": 1,
          "SrcCep": false,
          "SrcCepField": false,
          "CorreiosField": "NULL",
          "FieldsForIntegration": "Null",
          "ExternalCapture": null,
          "Oid": "fb99d246-3723-4de4-b8c3-09648860449a",
          "Mandatory": false,
          "Connect": false,
          "Caption": null,
          "Identifier": null,
          "Name": "Local de Nascimento",
          "CompanyId":
              "Certfy.Remote.Admin.Models.BusinessObjects.CompanyXpo(94612025-d6f5-4951-91f0-118016d92944)",
          "Order": 4
        },
        {
          "CaptureEntryType": "FormField",
          "Type": "Number",
          "Options": [],
          "FormFieldDynamic": {
            "Url": null,
            "FieldAttribute": null,
            "FormFieldDynamicControl": {
              "CaptureInput": "00000000-0000-0000-0000-000000000000",
              "VariableInput": null
            }
          },
          "OcrFieldName": "NULL",
          "InitialRange": 1,
          "FinalRange": 1,
          "SrcCep": false,
          "SrcCepField": false,
          "CorreiosField": "NULL",
          "FieldsForIntegration": "Null",
          "ExternalCapture": null,
          "Oid": "be86a25a-3d26-4491-9845-0bc045ef7215",
          "Mandatory": false,
          "Connect": false,
          "Caption": null,
          "Identifier": null,
          "Name": "Número",
          "CompanyId":
              "Certfy.Remote.Admin.Models.BusinessObjects.CompanyXpo(94612025-d6f5-4951-91f0-118016d92944)",
          "Order": 9
        },
        {
          "CaptureEntryType": "FormField",
          "Type": "Text",
          "Options": [],
          "FormFieldDynamic": {
            "Url": null,
            "FieldAttribute": null,
            "FormFieldDynamicControl": {
              "CaptureInput": "00000000-0000-0000-0000-000000000000",
              "VariableInput": null
            }
          },
          "OcrFieldName": "NULL",
          "InitialRange": 1,
          "FinalRange": 1,
          "SrcCep": false,
          "SrcCepField": false,
          "CorreiosField": "NULL",
          "FieldsForIntegration": "Null",
          "ExternalCapture": null,
          "Oid": "356dad1d-c54f-41ac-b097-69f4d73a2409",
          "Mandatory": false,
          "Connect": false,
          "Caption": null,
          "Identifier": null,
          "Name": "Logradouro",
          "CompanyId":
              "Certfy.Remote.Admin.Models.BusinessObjects.CompanyXpo(94612025-d6f5-4951-91f0-118016d92944)",
          "Order": 7
        },
        {
          "CaptureEntryType": "FormField",
          "Type": "Number",
          "Options": [],
          "FormFieldDynamic": {
            "Url": null,
            "FieldAttribute": null,
            "FormFieldDynamicControl": {
              "CaptureInput": "00000000-0000-0000-0000-000000000000",
              "VariableInput": null
            }
          },
          "OcrFieldName": "NULL",
          "InitialRange": 1,
          "FinalRange": 1,
          "SrcCep": false,
          "SrcCepField": false,
          "CorreiosField": "NULL",
          "FieldsForIntegration": "Null",
          "ExternalCapture": null,
          "Oid": "b439eac3-ec65-45b6-b51d-6a5faf55b214",
          "Mandatory": false,
          "Connect": false,
          "Caption": null,
          "Identifier": null,
          "Name": "CEP",
          "CompanyId":
              "Certfy.Remote.Admin.Models.BusinessObjects.CompanyXpo(94612025-d6f5-4951-91f0-118016d92944)",
          "Order": 5
        },
        {
          "CaptureEntryType": "FormField",
          "Type": "Number",
          "Options": [],
          "FormFieldDynamic": {
            "Url": null,
            "FieldAttribute": null,
            "FormFieldDynamicControl": {
              "CaptureInput": "00000000-0000-0000-0000-000000000000",
              "VariableInput": null
            }
          },
          "OcrFieldName": "NULL",
          "InitialRange": 1,
          "FinalRange": 1,
          "SrcCep": false,
          "SrcCepField": false,
          "CorreiosField": "NULL",
          "FieldsForIntegration": "Null",
          "ExternalCapture": null,
          "Oid": "6ee8b45c-a222-4652-9a63-71339fc47c64",
          "Mandatory": false,
          "Connect": false,
          "Caption": null,
          "Identifier": null,
          "Name": "DDD do Telefone",
          "CompanyId":
              "Certfy.Remote.Admin.Models.BusinessObjects.CompanyXpo(94612025-d6f5-4951-91f0-118016d92944)",
          "Order": 2
        },
        {
          "CaptureEntryType": "FormField",
          "Type": "Text",
          "Options": [],
          "FormFieldDynamic": {
            "Url": null,
            "FieldAttribute": null,
            "FormFieldDynamicControl": {
              "CaptureInput": "00000000-0000-0000-0000-000000000000",
              "VariableInput": null
            }
          },
          "OcrFieldName": "NULL",
          "InitialRange": 1,
          "FinalRange": 1,
          "SrcCep": false,
          "SrcCepField": false,
          "CorreiosField": "NULL",
          "FieldsForIntegration": "Null",
          "ExternalCapture": null,
          "Oid": "71ae733d-9f08-4949-bc9e-7de148f83174",
          "Mandatory": false,
          "Connect": false,
          "Caption": null,
          "Identifier": null,
          "Name": "Endereço do Usuário",
          "CompanyId":
              "Certfy.Remote.Admin.Models.BusinessObjects.CompanyXpo(94612025-d6f5-4951-91f0-118016d92944)",
          "Order": 8
        },
        {
          "CaptureEntryType": "FormField",
          "Type": "Email",
          "Options": [],
          "FormFieldDynamic": {
            "Url": null,
            "FieldAttribute": null,
            "FormFieldDynamicControl": {
              "CaptureInput": "00000000-0000-0000-0000-000000000000",
              "VariableInput": null
            }
          },
          "OcrFieldName": "NULL",
          "InitialRange": 1,
          "FinalRange": 1,
          "SrcCep": false,
          "SrcCepField": false,
          "CorreiosField": "NULL",
          "FieldsForIntegration": "Null",
          "ExternalCapture": null,
          "Oid": "bfbe1f27-4651-4497-9398-81dafce63b0c",
          "Mandatory": false,
          "Connect": false,
          "Caption": null,
          "Identifier": null,
          "Name": "E-mail",
          "CompanyId":
              "Certfy.Remote.Admin.Models.BusinessObjects.CompanyXpo(94612025-d6f5-4951-91f0-118016d92944)",
          "Order": 1
        },
        {
          "CaptureEntryType": "FormField",
          "Type": "Text",
          "Options": [],
          "FormFieldDynamic": {
            "Url": null,
            "FieldAttribute": null,
            "FormFieldDynamicControl": {
              "CaptureInput": "00000000-0000-0000-0000-000000000000",
              "VariableInput": null
            }
          },
          "OcrFieldName": "NULL",
          "InitialRange": 1,
          "FinalRange": 1,
          "SrcCep": false,
          "SrcCepField": false,
          "CorreiosField": "NULL",
          "FieldsForIntegration": "Null",
          "ExternalCapture": null,
          "Oid": "c1d0721d-950d-4771-ad7d-8916d89a7226",
          "Mandatory": false,
          "Connect": false,
          "Caption": null,
          "Identifier": null,
          "Name": "Bairro",
          "CompanyId":
              "Certfy.Remote.Admin.Models.BusinessObjects.CompanyXpo(94612025-d6f5-4951-91f0-118016d92944)",
          "Order": 6
        },
        {
          "CaptureEntryType": "FormField",
          "Type": "Number",
          "Options": [],
          "FormFieldDynamic": {
            "Url": null,
            "FieldAttribute": null,
            "FormFieldDynamicControl": {
              "CaptureInput": "00000000-0000-0000-0000-000000000000",
              "VariableInput": null
            }
          },
          "OcrFieldName": "NULL",
          "InitialRange": 1,
          "FinalRange": 1,
          "SrcCep": false,
          "SrcCepField": false,
          "CorreiosField": "NULL",
          "FieldsForIntegration": "Null",
          "ExternalCapture": null,
          "Oid": "1ff73352-05ac-430e-bf4f-cfa05e97ce8a",
          "Mandatory": false,
          "Connect": false,
          "Caption": null,
          "Identifier": null,
          "Name": "Número de Telefone",
          "CompanyId":
              "Certfy.Remote.Admin.Models.BusinessObjects.CompanyXpo(94612025-d6f5-4951-91f0-118016d92944)",
          "Order": 3
        }
      ],
      "IsExternalCapture": false,
      "OcrLink": false,
      "IdentificationDocumentCaptureEntryConfiguration": null,
      "Oid": "8866a5a5-66af-46cf-a36a-c303fd508a66",
      "Mandatory": true,
      "Connect": false,
      "Caption": "Informe seus dados para contato ",
      "Identifier": null,
      "Name": "Formulário de Dados para Contato",
      "CompanyId": "94612025-d6f5-4951-91f0-118016d92944",
      "Order": 6
    },
    {
      "CaptureEntryType": "Form",
      "Fields": [
        {
          "CaptureEntryType": "FormField",
          "Type": "DynamicSelect",
          "Options": [],
          "FormFieldDynamic": {
            "Url":
                "https://servicodados.ibge.gov.br/api/v1/localidades/estados/{ESTADO}/distritos",
            "FieldAttribute": "nome",
            "FormFieldDynamicControl": {
              "CaptureInput": "405f0274-001f-4f2b-afc6-63da2a6411ae",
              "VariableInput": "ESTADO"
            }
          },
          "OcrFieldName": "NULL",
          "InitialRange": 1,
          "FinalRange": 1,
          "SrcCep": false,
          "SrcCepField": false,
          "CorreiosField": "NULL",
          "FieldsForIntegration": "Null",
          "ExternalCapture": null,
          "Oid": "76c0c916-5fa4-4c33-bfcf-1e161cba9daf",
          "Mandatory": false,
          "Connect": false,
          "Caption": null,
          "Identifier": null,
          "Name": "Cidade onde nasceu o usuário ",
          "CompanyId":
              "Certfy.Remote.Admin.Models.BusinessObjects.CompanyXpo(94612025-d6f5-4951-91f0-118016d92944)",
          "Order": 10
        },
        {
          "CaptureEntryType": "FormField",
          "Type": "Text",
          "Options": [],
          "FormFieldDynamic": {
            "Url": null,
            "FieldAttribute": null,
            "FormFieldDynamicControl": {
              "CaptureInput": "00000000-0000-0000-0000-000000000000",
              "VariableInput": null
            }
          },
          "OcrFieldName": "NULL",
          "InitialRange": 1,
          "FinalRange": 1,
          "SrcCep": false,
          "SrcCepField": false,
          "CorreiosField": "NULL",
          "FieldsForIntegration": "Null",
          "ExternalCapture": null,
          "Oid": "0aee8932-4121-454e-8883-237c56a9d316",
          "Mandatory": false,
          "Connect": false,
          "Caption": null,
          "Identifier": null,
          "Name": "Nacionalidade",
          "CompanyId":
              "Certfy.Remote.Admin.Models.BusinessObjects.CompanyXpo(94612025-d6f5-4951-91f0-118016d92944)",
          "Order": 8
        },
        {
          "CaptureEntryType": "FormField",
          "Type": "Text",
          "Options": [],
          "FormFieldDynamic": {
            "Url": null,
            "FieldAttribute": null,
            "FormFieldDynamicControl": {
              "CaptureInput": "00000000-0000-0000-0000-000000000000",
              "VariableInput": null
            }
          },
          "OcrFieldName": "NULL",
          "InitialRange": 1,
          "FinalRange": 1,
          "SrcCep": false,
          "SrcCepField": false,
          "CorreiosField": "NULL",
          "FieldsForIntegration": "Null",
          "ExternalCapture": null,
          "Oid": "3411d4a9-9ac2-44f1-bae6-3d1d23b4d6d7",
          "Mandatory": false,
          "Connect": false,
          "Caption": null,
          "Identifier": null,
          "Name": "País",
          "CompanyId":
              "Certfy.Remote.Admin.Models.BusinessObjects.CompanyXpo(94612025-d6f5-4951-91f0-118016d92944)",
          "Order": 7
        },
        {
          "CaptureEntryType": "FormField",
          "Type": "DynamicSelect",
          "Options": [],
          "FormFieldDynamic": {
            "Url":
                "https://servicodados.ibge.gov.br/api/v1/localidades/estados",
            "FieldAttribute": "sigla",
            "FormFieldDynamicControl": {
              "CaptureInput": "00000000-0000-0000-0000-000000000000",
              "VariableInput": null
            }
          },
          "OcrFieldName": "NULL",
          "InitialRange": 1,
          "FinalRange": 1,
          "SrcCep": false,
          "SrcCepField": false,
          "CorreiosField": "NULL",
          "FieldsForIntegration": "Null",
          "ExternalCapture": null,
          "Oid": "405f0274-001f-4f2b-afc6-63da2a6411ae",
          "Mandatory": false,
          "Connect": false,
          "Caption": null,
          "Identifier": null,
          "Name": "Estado onde nasceu o usuário",
          "CompanyId":
              "Certfy.Remote.Admin.Models.BusinessObjects.CompanyXpo(94612025-d6f5-4951-91f0-118016d92944)",
          "Order": 9
        },
        {
          "CaptureEntryType": "FormField",
          "Type": "Text",
          "Options": [],
          "FormFieldDynamic": {
            "Url": null,
            "FieldAttribute": null,
            "FormFieldDynamicControl": {
              "CaptureInput": "00000000-0000-0000-0000-000000000000",
              "VariableInput": null
            }
          },
          "OcrFieldName": "NULL",
          "InitialRange": 1,
          "FinalRange": 1,
          "SrcCep": false,
          "SrcCepField": false,
          "CorreiosField": "NULL",
          "FieldsForIntegration": "Null",
          "ExternalCapture": null,
          "Oid": "b740a4fa-a2a6-4c64-9fc0-86269adc3ac0",
          "Mandatory": false,
          "Connect": false,
          "Caption": null,
          "Identifier": null,
          "Name": "Nome completo",
          "CompanyId":
              "Certfy.Remote.Admin.Models.BusinessObjects.CompanyXpo(94612025-d6f5-4951-91f0-118016d92944)",
          "Order": 1
        },
        {
          "CaptureEntryType": "FormField",
          "Type": "Text",
          "Options": [],
          "FormFieldDynamic": {
            "Url": null,
            "FieldAttribute": null,
            "FormFieldDynamicControl": {
              "CaptureInput": "00000000-0000-0000-0000-000000000000",
              "VariableInput": null
            }
          },
          "OcrFieldName": "NULL",
          "InitialRange": 1,
          "FinalRange": 1,
          "SrcCep": false,
          "SrcCepField": false,
          "CorreiosField": "NULL",
          "FieldsForIntegration": "Null",
          "ExternalCapture": null,
          "Oid": "93c583a6-e11f-4a8b-80a5-93919b6d71c1",
          "Mandatory": false,
          "Connect": false,
          "Caption": null,
          "Identifier": null,
          "Name": "Nome da sua mãe",
          "CompanyId":
              "Certfy.Remote.Admin.Models.BusinessObjects.CompanyXpo(94612025-d6f5-4951-91f0-118016d92944)",
          "Order": 6
        },
        {
          "CaptureEntryType": "FormField",
          "Type": "DateTime",
          "Options": [],
          "FormFieldDynamic": {
            "Url": null,
            "FieldAttribute": null,
            "FormFieldDynamicControl": {
              "CaptureInput": "00000000-0000-0000-0000-000000000000",
              "VariableInput": null
            }
          },
          "OcrFieldName": "NULL",
          "InitialRange": 1,
          "FinalRange": 1,
          "SrcCep": false,
          "SrcCepField": false,
          "CorreiosField": "NULL",
          "FieldsForIntegration": "Null",
          "ExternalCapture": null,
          "Oid": "8857ad0a-ccca-407a-b876-9e48e165e4cc",
          "Mandatory": false,
          "Connect": false,
          "Caption": null,
          "Identifier": null,
          "Name": "Data de Nascimento",
          "CompanyId":
              "Certfy.Remote.Admin.Models.BusinessObjects.CompanyXpo(94612025-d6f5-4951-91f0-118016d92944)",
          "Order": 3
        },
        {
          "CaptureEntryType": "FormField",
          "Type": "Select",
          "Options": [
            {
              "Name": "Masculino",
              "Order": 1,
              "Selected": false,
              "LinkCapture": []
            },
            {"Name": "Outro", "Order": 1, "Selected": false, "LinkCapture": []},
            {
              "Name": "Feminino",
              "Order": 1,
              "Selected": false,
              "LinkCapture": []
            },
            {
              "Name": "Prefiro não dizer",
              "Order": 1,
              "Selected": false,
              "LinkCapture": []
            }
          ],
          "FormFieldDynamic": {
            "Url": null,
            "FieldAttribute": null,
            "FormFieldDynamicControl": {
              "CaptureInput": "00000000-0000-0000-0000-000000000000",
              "VariableInput": null
            }
          },
          "OcrFieldName": "NULL",
          "InitialRange": 1,
          "FinalRange": 1,
          "SrcCep": false,
          "SrcCepField": false,
          "CorreiosField": "NULL",
          "FieldsForIntegration": "Null",
          "ExternalCapture": null,
          "Oid": "bcb5befd-b160-4e4e-8f25-c2e1e81585a0",
          "Mandatory": false,
          "Connect": false,
          "Caption": null,
          "Identifier": null,
          "Name": "Sexo",
          "CompanyId":
              "Certfy.Remote.Admin.Models.BusinessObjects.CompanyXpo(94612025-d6f5-4951-91f0-118016d92944)",
          "Order": 4
        },
        {
          "CaptureEntryType": "FormField",
          "Type": "Text",
          "Options": [],
          "FormFieldDynamic": {
            "Url": null,
            "FieldAttribute": null,
            "FormFieldDynamicControl": {
              "CaptureInput": "00000000-0000-0000-0000-000000000000",
              "VariableInput": null
            }
          },
          "OcrFieldName": "NULL",
          "InitialRange": 1,
          "FinalRange": 1,
          "SrcCep": false,
          "SrcCepField": false,
          "CorreiosField": "NULL",
          "FieldsForIntegration": "Null",
          "ExternalCapture": null,
          "Oid": "448bf232-a050-4fdb-af09-ceb3b8b92884",
          "Mandatory": false,
          "Connect": false,
          "Caption": null,
          "Identifier": null,
          "Name": "Nome do seu pai",
          "CompanyId":
              "Certfy.Remote.Admin.Models.BusinessObjects.CompanyXpo(94612025-d6f5-4951-91f0-118016d92944)",
          "Order": 5
        },
        {
          "CaptureEntryType": "FormField",
          "Type": "Cpf",
          "Options": [],
          "FormFieldDynamic": {
            "Url": null,
            "FieldAttribute": null,
            "FormFieldDynamicControl": {
              "CaptureInput": "00000000-0000-0000-0000-000000000000",
              "VariableInput": null
            }
          },
          "OcrFieldName": "NULL",
          "InitialRange": 1,
          "FinalRange": 1,
          "SrcCep": false,
          "SrcCepField": false,
          "CorreiosField": "NULL",
          "FieldsForIntegration": "Null",
          "ExternalCapture": null,
          "Oid": "46dfdccd-3f89-44b5-8c14-e693233f95e1",
          "Mandatory": false,
          "Connect": false,
          "Caption": null,
          "Identifier": null,
          "Name": "CPF",
          "CompanyId":
              "Certfy.Remote.Admin.Models.BusinessObjects.CompanyXpo(94612025-d6f5-4951-91f0-118016d92944)",
          "Order": 2
        }
      ],
      "IsExternalCapture": false,
      "OcrLink": false,
      "IdentificationDocumentCaptureEntryConfiguration": null,
      "Oid": "aa55cd14-10e8-4343-ae91-cc651bcc21b9",
      "Mandatory": true,
      "Connect": false,
      "Caption": "Informe seus dados pessoais ",
      "Identifier": null,
      "Name": "Formulário de Dados Pessoais",
      "CompanyId": "94612025-d6f5-4951-91f0-118016d92944",
      "Order": 5
    },
    {
      "CaptureEntryType": "Document",
      "CameraDirection": "Portrait",
      "CameraSelection": "FrontCamera",
      "Oid": "cb334d27-0176-4f9d-b2da-d44e8c25a748",
      "Mandatory": true,
      "Connect": false,
      "Caption": "Capture uma foto do seu documento de identificação ",
      "Identifier": null,
      "Name": "Documento de Identificação ",
      "CompanyId": "94612025-d6f5-4951-91f0-118016d92944",
      "Order": 3
    },
    {
      "CaptureEntryType": "IdentificationDocument",
      "Oid": "89b2d0fa-ecd6-4b11-bea0-f18fc6166672",
      "Mandatory": false,
      "Connect": false,
      "Caption": "CNH ou RG",
      "Identifier": null,
      "Name": "CNH ou RG",
      "CompanyId": "94612025-d6f5-4951-91f0-118016d92944",
      "Order": 9
    },
    {
      "CaptureEntryType": "Form",
      "Fields": [
        {
          "CaptureEntryType": "FormField",
          "Type": "DynamicSelect",
          "Options": [],
          "FormFieldDynamic": {
            "Url":
                "https://servicodados.ibge.gov.br/api/v1/localidades/estados",
            "FieldAttribute": "sigla",
            "FormFieldDynamicControl": {
              "CaptureInput": "00000000-0000-0000-0000-000000000000",
              "VariableInput": null
            }
          },
          "OcrFieldName": "NULL",
          "InitialRange": 1,
          "FinalRange": 1,
          "SrcCep": false,
          "SrcCepField": false,
          "CorreiosField": "NULL",
          "FieldsForIntegration": "Null",
          "ExternalCapture": null,
          "Oid": "6dc2c990-cd57-47bf-8c7a-346c7f08297b",
          "Mandatory": false,
          "Connect": false,
          "Caption": null,
          "Identifier": null,
          "Name": "Estado do Documento",
          "CompanyId":
              "Certfy.Remote.Admin.Models.BusinessObjects.CompanyXpo(94612025-d6f5-4951-91f0-118016d92944)",
          "Order": 3
        },
        {
          "CaptureEntryType": "FormField",
          "Type": "Text",
          "Options": [],
          "FormFieldDynamic": {
            "Url": null,
            "FieldAttribute": null,
            "FormFieldDynamicControl": {
              "CaptureInput": "00000000-0000-0000-0000-000000000000",
              "VariableInput": null
            }
          },
          "OcrFieldName": "NULL",
          "InitialRange": 1,
          "FinalRange": 1,
          "SrcCep": false,
          "SrcCepField": false,
          "CorreiosField": "NULL",
          "FieldsForIntegration": "Null",
          "ExternalCapture": null,
          "Oid": "73cb1c21-1ef6-43e4-a30e-45104a18814c",
          "Mandatory": false,
          "Connect": false,
          "Caption": null,
          "Identifier": null,
          "Name": "Número do Documento",
          "CompanyId":
              "Certfy.Remote.Admin.Models.BusinessObjects.CompanyXpo(94612025-d6f5-4951-91f0-118016d92944)",
          "Order": 4
        },
        {
          "CaptureEntryType": "FormField",
          "Type": "Select",
          "Options": [
            {"Name": "CNH", "Order": 1, "Selected": false, "LinkCapture": []},
            {
              "Name": "Passaporte",
              "Order": 1,
              "Selected": false,
              "LinkCapture": []
            },
            {
              "Name":
                  "Certificado de Dispensa de Incorporação (\"Certificado de Reservista\")",
              "Order": 1,
              "Selected": false,
              "LinkCapture": []
            },
            {
              "Name": "Carteira de Identidade",
              "Order": 1,
              "Selected": false,
              "LinkCapture": []
            },
            {
              "Name": "Carteira de Trabalho",
              "Order": 1,
              "Selected": false,
              "LinkCapture": []
            }
          ],
          "FormFieldDynamic": {
            "Url": null,
            "FieldAttribute": null,
            "FormFieldDynamicControl": {
              "CaptureInput": "00000000-0000-0000-0000-000000000000",
              "VariableInput": null
            }
          },
          "OcrFieldName": "NULL",
          "InitialRange": 1,
          "FinalRange": 1,
          "SrcCep": false,
          "SrcCepField": false,
          "CorreiosField": "NULL",
          "FieldsForIntegration": "Null",
          "ExternalCapture": null,
          "Oid": "132c9a99-b533-41c5-93c1-75fccc612d88",
          "Mandatory": false,
          "Connect": false,
          "Caption": null,
          "Identifier": null,
          "Name": "Tipo de Documento",
          "CompanyId":
              "Certfy.Remote.Admin.Models.BusinessObjects.CompanyXpo(94612025-d6f5-4951-91f0-118016d92944)",
          "Order": 1
        },
        {
          "CaptureEntryType": "FormField",
          "Type": "Text",
          "Options": [],
          "FormFieldDynamic": {
            "Url": null,
            "FieldAttribute": null,
            "FormFieldDynamicControl": {
              "CaptureInput": "00000000-0000-0000-0000-000000000000",
              "VariableInput": null
            }
          },
          "OcrFieldName": "NULL",
          "InitialRange": 1,
          "FinalRange": 1,
          "SrcCep": false,
          "SrcCepField": false,
          "CorreiosField": "NULL",
          "FieldsForIntegration": "Null",
          "ExternalCapture": null,
          "Oid": "96f4ff3a-ad03-46ed-a995-a3de34a96589",
          "Mandatory": false,
          "Connect": false,
          "Caption": null,
          "Identifier": null,
          "Name": "Órgão do Documento",
          "CompanyId":
              "Certfy.Remote.Admin.Models.BusinessObjects.CompanyXpo(94612025-d6f5-4951-91f0-118016d92944)",
          "Order": 2
        }
      ],
      "IsExternalCapture": false,
      "OcrLink": false,
      "IdentificationDocumentCaptureEntryConfiguration": null,
      "Oid": "a242dd97-8051-4f49-b6c6-f6eea773a825",
      "Mandatory": true,
      "Connect": false,
      "Caption": "Informe os dados do seu documento ",
      "Identifier": null,
      "Name": "Formulário de Dados do Documento ",
      "CompanyId": "94612025-d6f5-4951-91f0-118016d92944",
      "Order": 7
    },
    {
      "CaptureEntryType": "Document",
      "CameraDirection": "Portrait",
      "CameraSelection": "FrontCamera",
      "Oid": "1acd6d0d-c990-4e3d-9bd6-f82a48b0ac6f",
      "Mandatory": true,
      "Connect": false,
      "Caption": "Capture uma foto do seu comprovante de residência",
      "Identifier": null,
      "Name": "Comprovante de Residência",
      "CompanyId": "94612025-d6f5-4951-91f0-118016d92944",
      "Order": 2
    },
    {
      "CaptureEntryType": "FaceMatch",
      "ReferenceCapture": "Coletar Face do Usuário",
      "ValidateIcaoFeatures": true,
      "Oid": "f9f2a944-f3e3-42e3-a4f1-b13072cccd8e",
      "Mandatory": true,
      "Connect": false,
      "Caption": "Capture sua face  Match",
      "Identifier": null,
      "Name": "Coletar Face do Usuário Match",
      "CompanyId":
          "Certfy.Remote.Admin.Models.BusinessObjects.CompanyXpo(94612025-d6f5-4951-91f0-118016d92944)",
      "Order": 1
    },
    {
      "CaptureEntryType": "FingerprintMatch",
      "ReferenceCapture": "Capturar Impressão Digital - Mão Esquerda",
      "ApplyNFIQ": false,
      "Oid": "d5e32f5d-1e58-46e0-9db8-797ed493acea",
      "Mandatory": true,
      "Connect": false,
      "Caption": "Capture suas digitais da mão esquerda Match",
      "Identifier": null,
      "Name": "Capturar Impressão Digital - Mão Esquerda Match",
      "CompanyId":
          "Certfy.Remote.Admin.Models.BusinessObjects.CompanyXpo(94612025-d6f5-4951-91f0-118016d92944)",
      "Order": 4
    }
  ]
}
